linguistics/__init__.py
linguistics/tokenize_function.py
linguistics/bert/BertVectorizer.py
linguistics/bert/BertVectorizerModel.py
linguistics/bert/__init__.py
linguistics/document/BasicToken.py
linguistics/document/Document.py
linguistics/document/DocumentObject.py
linguistics/document/Entity.py
linguistics/document/EntityChunk.py
linguistics/document/EntityType.py
linguistics/document/Linguist.py
linguistics/document/NounChunk.py
linguistics/document/Sentence.py
linguistics/document/TokenSpan.py
linguistics/document/__init__.py
linguistics/document/dependency_definitions.py
linguistics/document/join_punctuation.py
linguistics/document/part_of_speach_definitions.py
linguistics/document/remove_list_duplicates.py
linguistics/document/split_into_sentences.py
linguistics/english/__init__.py
linguistics/english/get_pronoun_stop_words_function.py
linguistics/google/GoogleCloud.py
linguistics/google/GoogleDocument.py
linguistics/google/GoogleDocumentObject.py
linguistics/google/GoogleEntity.py
linguistics/google/GoogleSentence.py
linguistics/google/GoogleSentiment.py
linguistics/google/GoogleToken.py
linguistics/google/GoogleTokenSpan.py
linguistics/google/__init__.py
linguistics/google/analyze.py
linguistics/repustate/Repustate.py
linguistics/repustate/__init__.py
linguistics/similarity/Sentence.py
linguistics/similarity/Word.py
linguistics/similarity/__init__.py
linguistics/similarity/convert_score_and_distance_functions.py
linguistics/similarity/find_most_similar.py
linguistics/similarity/get_char_by_char_equality.py
linguistics/similarity/get_sentence_similarity.py
linguistics/similarity/get_similarity.py
linguistics/similarity/get_string_similarity.py
linguistics/similarity/jaro_winkler.py
linguistics/similarity/levenshtein.py
linguistics-2022.5.8.dist-info/LICENSE
linguistics-2022.5.8.dist-info/METADATA
linguistics-2022.5.8.dist-info/WHEEL
linguistics-2022.5.8.dist-info/top_level.txt
linguistics-2022.5.8.dist-info/RECORD
