Metadata-Version: 2.1
Name: linguistics
Version: 2022.5.8
Summary: Python library for natural language processing
Home-page: https://github.com/idin/linguistics
Author: Idin
Author-email: py@idin.ca
License: MIT
Platform: UNKNOWN
Classifier: Development Status :: 3 - Alpha
Classifier: Intended Audience :: Developers
Classifier: Programming Language :: Python :: 3 :: Only
Classifier: Programming Language :: Python :: 3.6
Classifier: Programming Language :: Python :: 3.7
Classifier: Topic :: Software Development :: Libraries :: Python Modules
Requires-Python: ~=3.6
Requires-Dist: abstract
Requires-Dist: spacy
Requires-Dist: requests
Requires-Dist: jellyfish
Requires-Dist: editdistance
Requires-Dist: chronometry
Requires-Dist: slytherin
Requires-Dist: numpy
Requires-Dist: pandas
Requires-Dist: torch
Requires-Dist: transformers
